jaqpotpy/__init__.py
jaqpotpy/jaqpot.py
jaqpotpy/jaqpot_local.py
jaqpotpy/.vscode/launch.json
jaqpotpy/api/__init__.py
jaqpotpy/api/get_installed_libraries.py
jaqpotpy/api/model_to_b64encoding.py
jaqpotpy/aws/s3.py
jaqpotpy/colorlog/__init__.py
jaqpotpy/colorlog/colorlog.py
jaqpotpy/colorlog/escape_codes.py
jaqpotpy/colorlog/logging.py
jaqpotpy/datasets/__init__.py
jaqpotpy/datasets/dataset_base.py
jaqpotpy/datasets/graph_pyg_dataset.py
jaqpotpy/datasets/jaqpot_tabular_dataset.py
jaqpotpy/datasets/jaqpot_tensor_dataset.py
jaqpotpy/datasets/tokenizer_dataset.py
jaqpotpy/datasets/tests/__init__.py
jaqpotpy/datasets/tests/test_JaqpotTabularDataset.py
jaqpotpy/descriptors/__init__.py
jaqpotpy/descriptors/base_classes.py
jaqpotpy/descriptors/graph/__init__.py
jaqpotpy/descriptors/graph/graph_featurizer.py
jaqpotpy/descriptors/molecular/__init__.py
jaqpotpy/descriptors/molecular/maccs_keys_fingerprints.py
jaqpotpy/descriptors/molecular/mordred.py
jaqpotpy/descriptors/molecular/rdkit.py
jaqpotpy/descriptors/molecular/topological_fingerprints.py
jaqpotpy/descriptors/tests/__init__.py
jaqpotpy/descriptors/tests/test_MACCS_key_fingerprints.py
jaqpotpy/descriptors/tests/test_graph_featurizer.py
jaqpotpy/descriptors/tests/test_mordred_descriptors.py
jaqpotpy/descriptors/tests/test_rdkit_descriptors.py
jaqpotpy/descriptors/tests/test_topological_fingerprints.py
jaqpotpy/descriptors/tokenizer/__init__.py
jaqpotpy/descriptors/tokenizer/smiles_tokenizer.py
jaqpotpy/doa/__init__.py
jaqpotpy/doa/doa.py
jaqpotpy/doa/tests/__init__.py
jaqpotpy/doa/tests/test_doa.py
jaqpotpy/exceptions/__init__.py
jaqpotpy/exceptions/exceptions.py
jaqpotpy/helpers/__init__.py
jaqpotpy/helpers/logging.py
jaqpotpy/helpers/url_utils.py
jaqpotpy/inference/__init__.py
jaqpotpy/inference/service.py
jaqpotpy/inference/core/__init__.py
jaqpotpy/inference/core/model_loader.py
jaqpotpy/inference/core/predict_methods.py
jaqpotpy/inference/core/preprocessor_utils.py
jaqpotpy/inference/handlers/__init__.py
jaqpotpy-7.1.0.dist-info/METADATA
jaqpotpy-7.1.0.dist-info/WHEEL
jaqpotpy-7.1.0.dist-info/licenses/LICENSE
jaqpotpy-7.1.0.dist-info/RECORD
