Metadata-Version: 2.4
Name: jaqpotpy
Version: 7.1.0
Summary: Client library for managing machine learning models on the Jaqpot platform
Project-URL: Homepage, https://github.com/ntua-unit-of-control-and-informatics/jaqpotpy
Author-email: Unit of Process Control and Informatics | National Technical University of Athens <upci.ntua@gmail.com>
License-Expression: MIT
License-File: LICENSE
Classifier: License :: OSI Approved :: MIT License
Classifier: Operating System :: OS Independent
Classifier: Programming Language :: Python :: 3
Requires-Python: >=3.7
Requires-Dist: httpx
Requires-Dist: jaqpot-api-client>=6.43.0
Requires-Dist: jaqpot-python-sdk>=6.0.2
Requires-Dist: onnx==1.18.0
Requires-Dist: onnxmltools>=1.12.0
Requires-Dist: onnxruntime>=1.19.0
Requires-Dist: pandas>=2.2.2
Requires-Dist: polling2>=0.5.0
Requires-Dist: pydantic>=2.0
Requires-Dist: python-keycloak>=4.3.0
Requires-Dist: rdkit>=2023.9.6
Requires-Dist: requests>=2.32.2
Requires-Dist: scikit-learn>=1.5.0
Requires-Dist: setuptools>=75.0.0
Requires-Dist: skl2onnx>=1.17.0
Requires-Dist: torch-geometric>=2.5.0
Requires-Dist: torch>=2.0.0
Requires-Dist: xgboost>=2.1.1
